bio_transformations/__init__.py
bio_transformations/bio_config.py
bio_transformations/bio_converter.py
bio_transformations/bio_module.py
pytorch_bio_transformations-0.0.5.dist-info/METADATA
pytorch_bio_transformations-0.0.5.dist-info/WHEEL
pytorch_bio_transformations-0.0.5.dist-info/licenses/LICENSE
pytorch_bio_transformations-0.0.5.dist-info/RECORD
