Metadata-Version: 2.4
Name: pytorch_bio_transformations
Version: 0.0.5
Summary: BioLearn: Biologically Inspired Neural Network Modifications
Project-URL: Homepage, https://github.com/CeadeS/pytorch_bio_transformations
Project-URL: Issues, https://github.com/CeadeS/pytorch_bio_transformations
Project-URL: Docs, https://CeadeS.github.io/pytorch_bio_transformations
Author-email: Martin Hofmann <Martin.Hofmann@tu-ilmenau.de>
License-File: LICENSE
Classifier: Development Status :: 1 - Planning
Classifier: Intended Audience :: Science/Research
Classifier: License :: OSI Approved :: MIT License
Classifier: Operating System :: POSIX :: Linux
Classifier: Programming Language :: Python :: 3.7
Classifier: Programming Language :: Python :: 3.8
Classifier: Programming Language :: Python :: 3.10
Classifier: Programming Language :: Python :: 3.11
Classifier: Programming Language :: Python :: 3.12
Requires-Python: >=3.8
